django_celery_results/__init__.py
django_celery_results/admin.py
django_celery_results/apps.py
django_celery_results/managers.py
django_celery_results/models.py
django_celery_results/urls.py
django_celery_results/utils.py
django_celery_results/views.py
django_celery_results/backends/__init__.py
django_celery_results/backends/cache.py
django_celery_results/backends/database.py
django_celery_results/locale/es/LC_MESSAGES/django.po
django_celery_results/locale/pt_BR/LC_MESSAGES/django.po
django_celery_results/locale/ru/LC_MESSAGES/django.po
django_celery_results/locale/zh_Hans/LC_MESSAGES/django.po
django_celery_results/migrations/0001_initial.py
django_celery_results/migrations/0002_add_task_name_args_kwargs.py
django_celery_results/migrations/0003_auto_20181106_1101.py
django_celery_results/migrations/0004_auto_20190516_0412.py
django_celery_results/migrations/0005_taskresult_worker.py
django_celery_results/migrations/0006_taskresult_date_created.py
django_celery_results/migrations/0007_remove_taskresult_hidden.py
django_celery_results/migrations/0008_chordcounter.py
django_celery_results/migrations/0009_groupresult.py
django_celery_results/migrations/0010_remove_duplicate_indices.py
django_celery_results/migrations/0011_taskresult_periodic_task_name.py
django_celery_results/migrations/__init__.py
django_celery_results-2.5.0.dist-info/AUTHORS
django_celery_results-2.5.0.dist-info/LICENSE
django_celery_results-2.5.0.dist-info/METADATA
django_celery_results-2.5.0.dist-info/WHEEL
django_celery_results-2.5.0.dist-info/entry_points.txt
django_celery_results-2.5.0.dist-info/top_level.txt
django_celery_results-2.5.0.dist-info/RECORD
